odoo/addons/account_voucher_killer/README.rst
odoo/addons/account_voucher_killer/__init__.py
odoo/addons/account_voucher_killer/__manifest__.py
odoo/addons/account_voucher_killer/i18n/account_voucher_killer.pot
odoo/addons/account_voucher_killer/i18n/es.po
odoo/addons/account_voucher_killer/i18n/pt_BR.po
odoo/addons/account_voucher_killer/i18n/sl.po
odoo/addons/account_voucher_killer/readme/CONFIGURE.rst
odoo/addons/account_voucher_killer/readme/CONTRIBUTORS.rst
odoo/addons/account_voucher_killer/readme/DESCRIPTION.rst
odoo/addons/account_voucher_killer/security/invoice_data.xml
odoo/addons/account_voucher_killer/static/description/icon.png
odoo/addons/account_voucher_killer/static/description/index.html
odoo/addons/account_voucher_killer/view/invoice_view.xml
odoo11_addon_account_voucher_killer-11.0.1.0.0.99.dev6.dist-info/METADATA
odoo11_addon_account_voucher_killer-11.0.1.0.0.99.dev6.dist-info/WHEEL
odoo11_addon_account_voucher_killer-11.0.1.0.0.99.dev6.dist-info/top_level.txt
odoo11_addon_account_voucher_killer-11.0.1.0.0.99.dev6.dist-info/RECORD
